manage_iocs/__init__.py
manage_iocs/__main__.py
manage_iocs/_version.py
manage_iocs/commands.py
manage_iocs/utils.py
manage_iocs-0.1.0.dist-info/licenses/LICENSE
manage_iocs-0.1.0.dist-info/METADATA
manage_iocs-0.1.0.dist-info/WHEEL
manage_iocs-0.1.0.dist-info/entry_points.txt
manage_iocs-0.1.0.dist-info/top_level.txt
manage_iocs-0.1.0.dist-info/RECORD
