Metadata-Version: 2.4
Name: manage-iocs
Version: 0.1.0
Summary: CLI utility for auto-creating phoebus engineering screens from EPICS db templates
Author-email: Jakub Wlodek <jwlodek@bnl.gov>
License: BSD 3-Clause License
Project-URL: GitHub, https://github.com/NSLS2/manage-iocs
Classifier: Development Status :: 3 - Alpha
Classifier: License :: OSI Approved :: Apache Software License
Classifier: Programming Language :: Python :: 3.11
Classifier: Programming Language :: Python :: 3.12
Classifier: Programming Language :: Python :: 3.13
Requires-Python: >=3.11
License-File: LICENSE
Requires-Dist: pyyaml
Provides-Extra: dev
Requires-Dist: copier; extra == "dev"
Requires-Dist: pipdeptree; extra == "dev"
Requires-Dist: pre-commit; extra == "dev"
Requires-Dist: pyright; extra == "dev"
Requires-Dist: pytest; extra == "dev"
Requires-Dist: pytest-cov; extra == "dev"
Requires-Dist: ruff; extra == "dev"
Requires-Dist: tox-direct; extra == "dev"
Requires-Dist: types-mock; extra == "dev"
Requires-Dist: import-linter; extra == "dev"
Dynamic: license-file
